{"app":{"version":1,"foundation_config":{"ServiceName":"rails-otto","ServicePort":0,"ServiceTags":null},"dev_dep_fragment_path":"","foundation_results":null},"app_deps":{"606fbb11-c0c1-a64e-f412-701e345833e6":{"version":1,"foundation_config":{"ServiceName":"postgresql","ServicePort":0,"ServiceTags":null},"dev_dep_fragment_path":"/Users/thiago/Projects/Ruby/rails-otto/.otto/compiled/dep-606fbb11-c0c1-a64e-f412-701e345833e6/dev-dep/Vagrantfile.fragment","foundation_results":null}},"infra":null,"foundations":{"consul":null}}
